pyarcticspas/__init__.py
pyarcticspas/const.py
pyarcticspas/error.py
pyarcticspas/py.typed
pyarcticspas/spa.py
tests/__init__.py
tests/test_async.py
tests/test_sync.py
pyarcticspas-0.2.4.dist-info/LICENSE
pyarcticspas-0.2.4.dist-info/METADATA
pyarcticspas-0.2.4.dist-info/WHEEL
pyarcticspas-0.2.4.dist-info/top_level.txt
pyarcticspas-0.2.4.dist-info/RECORD
