Metadata-Version: 2.1
Name: pyarcticspas
Version: 0.2.4
Summary: A high-level client library for accessing Arctic Spas API
Requires-Python: >=3.8, <4
License-File: LICENSE
Requires-Dist: arcticspas >=2.0
